tests/__init__.py
tests/test_normalize.py
tsnorm/__init__.py
tsnorm/normalize.py
tsnorm/spacy_model.py
tsnorm/types.py
tsnorm/dictionary/__init__.py
tsnorm/dictionary/lemmas.dat
tsnorm/dictionary/wordforms.dat
tsnorm-1.1.2.dist-info/LICENSE
tsnorm-1.1.2.dist-info/METADATA
tsnorm-1.1.2.dist-info/WHEEL
tsnorm-1.1.2.dist-info/top_level.txt
tsnorm-1.1.2.dist-info/zip-safe
tsnorm-1.1.2.dist-info/RECORD
