Metadata-Version: 2.1
Name: tsnorm
Version: 1.1.2
Summary: A library to put stress marks in Russian text
Home-page: https://github.com/NetherQuartz/TextForSpeechNormalizer
Author: Vladimir Larkin
Author-email: vladimir@larkin.one
Keywords: nlp,accentuation,wiktionary,russian-language,setuptools,spacy
Classifier: Programming Language :: Python :: 3 :: Only
Classifier: Typing :: Typed
Classifier: Topic :: Text Processing :: Linguistic
Classifier: Natural Language :: Russian
Classifier: Intended Audience :: Developers
Classifier: Intended Audience :: Science/Research
Classifier: Development Status :: 5 - Production/Stable
Classifier: License :: OSI Approved :: MIT License
Requires-Python: <3.13,>=3.10
License-File: LICENSE
Requires-Dist: spacy>=3.5.0
